depthviz/__init__.py
depthviz/__main__.py
depthviz/__version__.py
depthviz/assets/fonts/Open_Sans/OFL.txt
"depthviz/assets/fonts/Open_Sans/OpenSans-Italic-VariableFont_wdth,wght.ttf"
"depthviz/assets/fonts/Open_Sans/OpenSans-VariableFont_wdth,wght.ttf"
depthviz/assets/fonts/Open_Sans/README.txt
depthviz/assets/fonts/Open_Sans/static/OpenSans-Bold.ttf
depthviz/assets/fonts/Open_Sans/static/OpenSans-BoldItalic.ttf
depthviz/assets/fonts/Open_Sans/static/OpenSans-ExtraBold.ttf
depthviz/assets/fonts/Open_Sans/static/OpenSans-ExtraBoldItalic.ttf
depthviz/assets/fonts/Open_Sans/static/OpenSans-Italic.ttf
depthviz/assets/fonts/Open_Sans/static/OpenSans-Light.ttf
depthviz/assets/fonts/Open_Sans/static/OpenSans-LightItalic.ttf
depthviz/assets/fonts/Open_Sans/static/OpenSans-Medium.ttf
depthviz/assets/fonts/Open_Sans/static/OpenSans-MediumItalic.ttf
depthviz/assets/fonts/Open_Sans/static/OpenSans-Regular.ttf
depthviz/assets/fonts/Open_Sans/static/OpenSans-SemiBold.ttf
depthviz/assets/fonts/Open_Sans/static/OpenSans-SemiBoldItalic.ttf
depthviz/assets/fonts/Open_Sans/static/OpenSans_Condensed-Bold.ttf
depthviz/assets/fonts/Open_Sans/static/OpenSans_Condensed-BoldItalic.ttf
depthviz/assets/fonts/Open_Sans/static/OpenSans_Condensed-ExtraBold.ttf
depthviz/assets/fonts/Open_Sans/static/OpenSans_Condensed-ExtraBoldItalic.ttf
depthviz/assets/fonts/Open_Sans/static/OpenSans_Condensed-Italic.ttf
depthviz/assets/fonts/Open_Sans/static/OpenSans_Condensed-Light.ttf
depthviz/assets/fonts/Open_Sans/static/OpenSans_Condensed-LightItalic.ttf
depthviz/assets/fonts/Open_Sans/static/OpenSans_Condensed-Medium.ttf
depthviz/assets/fonts/Open_Sans/static/OpenSans_Condensed-MediumItalic.ttf
depthviz/assets/fonts/Open_Sans/static/OpenSans_Condensed-Regular.ttf
depthviz/assets/fonts/Open_Sans/static/OpenSans_Condensed-SemiBold.ttf
depthviz/assets/fonts/Open_Sans/static/OpenSans_Condensed-SemiBoldItalic.ttf
depthviz/assets/fonts/Open_Sans/static/OpenSans_SemiCondensed-Bold.ttf
depthviz-0.6.2.dist-info/METADATA
depthviz-0.6.2.dist-info/WHEEL
depthviz-0.6.2.dist-info/entry_points.txt
depthviz-0.6.2.dist-info/licenses/AUTHORS.md
depthviz-0.6.2.dist-info/licenses/LICENSE
depthviz-0.6.2.dist-info/RECORD
