Metadata-Version: 2.4
Name: depthviz
Version: 0.6.2
Summary: Visualize your depth for your freediving videos: Works with or without dive computers.
License: Apache-2.0
License-File: AUTHORS.md
License-File: LICENSE
Keywords: freediving,dive,video,overlay,depth,dive-computer,dive-log,hud
Author: Noppanut Ploywong
Author-email: noppanut.connect@gmail.com
Requires-Python: >=3.9,<3.14
Classifier: Development Status :: 5 - Production/Stable
Classifier: Intended Audience :: Developers
Classifier: Intended Audience :: End Users/Desktop
Classifier: License :: OSI Approved :: Apache Software License
Classifier: Natural Language :: English
Classifier: Programming Language :: Python
Classifier: Programming Language :: Python :: 3
Classifier: Programming Language :: Python :: 3.9
Classifier: Programming Language :: Python :: 3.10
Classifier: Programming Language :: Python :: 3.11
Classifier: Programming Language :: Python :: 3.12
Classifier: Programming Language :: Python :: 3.13
Classifier: Topic :: Multimedia
Classifier: Topic :: Multimedia :: Video
Requires-Dist: colorama (>=0.4.6,<0.5.0)
Requires-Dist: garmin-fit-sdk (>=21.158.0,<22.0.0)
Requires-Dist: moviepy (==2.1.1)
Requires-Dist: tqdm (>=4.67.1,<5.0.0)
Project-URL: Repository, https://github.com/noppanut15/depthviz
